confstack/__init__.py
confstack/confstack.py
confstack-0.1.0.dist-info/licenses/LICENSE
confstack-0.1.0.dist-info/METADATA
confstack-0.1.0.dist-info/WHEEL
confstack-0.1.0.dist-info/top_level.txt
confstack-0.1.0.dist-info/RECORD
