Metadata-Version: 2.4
Name: confstack
Version: 0.1.0
Summary: Multi-Layer Configuration Architecture with priority order: in-code defaults, config file, env vars, and CLI.
Author-email: Lam Nguyenx <lamfm95@gmail.com>
License: MIT
Project-URL: Homepage, https://github.com/lamnguyenx/confstack
Project-URL: Repository, https://github.com/lamnguyenx/confstack
Project-URL: Issues, https://github.com/lamnguyenx/confstack/issues
Project-URL: Documentation, https://github.com/lamnguyenx/confstack/wiki
Keywords: configuration,settings,pydantic,stack,env-vars
Classifier: Development Status :: 4 - Beta
Classifier: Intended Audience :: Developers
Classifier: License :: OSI Approved :: MIT License
Classifier: Programming Language :: Python :: 3
Classifier: Programming Language :: Python :: 3.9
Classifier: Programming Language :: Python :: 3.10
Classifier: Programming Language :: Python :: 3.11
Classifier: Programming Language :: Python :: 3.12
Classifier: Programming Language :: Python :: 3.13
Classifier: Programming Language :: Python :: 3.14
Classifier: Topic :: Software Development :: Libraries :: Python Modules
Requires-Python: >=3.9
License-File: LICENSE
Requires-Dist: pydantic>=2.10
Requires-Dist: pandas>=2.2.0
Requires-Dist: htpy>=1.0
Dynamic: license-file
